cibuildwheel/__init__.py
cibuildwheel/__main__.py
cibuildwheel/architecture.py
cibuildwheel/bashlex_eval.py
cibuildwheel/ci.py
cibuildwheel/environment.py
cibuildwheel/errors.py
cibuildwheel/extra.py
cibuildwheel/frontend.py
cibuildwheel/logger.py
cibuildwheel/oci_container.py
cibuildwheel/options.py
cibuildwheel/projectfiles.py
cibuildwheel/py.typed
cibuildwheel/schema.py
cibuildwheel/selector.py
cibuildwheel/typing.py
cibuildwheel/venv.py
cibuildwheel/platforms/__init__.py
cibuildwheel/platforms/android.py
cibuildwheel/platforms/ios.py
cibuildwheel/platforms/linux.py
cibuildwheel/platforms/macos.py
cibuildwheel/platforms/pyodide.py
cibuildwheel/platforms/windows.py
cibuildwheel/resources/_cross_venv.pth
cibuildwheel/resources/_cross_venv.py
cibuildwheel/resources/build-platforms.toml
cibuildwheel/resources/cibuildwheel.schema.json
cibuildwheel/resources/constraints-pyodide312.txt
cibuildwheel/resources/constraints-pyodide313.txt
cibuildwheel/resources/constraints-python310.txt
cibuildwheel/resources/constraints-python311.txt
cibuildwheel/resources/constraints-python312.txt
cibuildwheel/resources/constraints-python313.txt
cibuildwheel/resources/constraints-python314.txt
cibuildwheel/resources/constraints-python38.txt
cibuildwheel/resources/constraints-python39.txt
cibuildwheel/resources/constraints.in
cibuildwheel/resources/constraints.txt
cibuildwheel/resources/defaults.toml
cibuildwheel/resources/free-threaded-enable-313.xml
cibuildwheel/resources/free-threaded-enable-314.xml
cibuildwheel/resources/install_certifi.py
cibuildwheel/resources/nodejs.toml
cibuildwheel/resources/pinned_docker_images.cfg
cibuildwheel/resources/python-build-standalone-releases.json
cibuildwheel/resources/testing_temp_dir_file.py
cibuildwheel/resources/virtualenv.toml
cibuildwheel/util/__init__.py
cibuildwheel/util/cmd.py
cibuildwheel/util/file.py
cibuildwheel/util/helpers.py
cibuildwheel/util/packaging.py
cibuildwheel/util/python_build_standalone.py
cibuildwheel/util/resources.py
cibuildwheel-3.3.1.dist-info/METADATA
cibuildwheel-3.3.1.dist-info/WHEEL
cibuildwheel-3.3.1.dist-info/entry_points.txt
cibuildwheel-3.3.1.dist-info/licenses/LICENSE
cibuildwheel-3.3.1.dist-info/RECORD
