Metadata-Version: 2.4
Name: cibuildwheel
Version: 3.3.1
Summary: Build Python wheels on CI with minimal configuration.
Project-URL: Changelog, https://github.com/pypa/cibuildwheel#changelog
Project-URL: Documentation, https://cibuildwheel.pypa.io
Project-URL: Homepage, https://github.com/pypa/cibuildwheel
Author-email: Joe Rickerby <joerick@mac.com>
License-Expression: BSD-2-Clause
License-File: LICENSE
Keywords: ci,linux,macos,packaging,pypi,travis,wheel,windows
Classifier: Development Status :: 5 - Production/Stable
Classifier: Intended Audience :: Developers
Classifier: Natural Language :: English
Classifier: Programming Language :: Python :: 3
Classifier: Programming Language :: Python :: 3 :: Only
Classifier: Programming Language :: Python :: 3.11
Classifier: Programming Language :: Python :: 3.12
Classifier: Programming Language :: Python :: 3.13
Classifier: Programming Language :: Python :: 3.14
Classifier: Programming Language :: Python :: Implementation :: CPython
Classifier: Topic :: Software Development :: Build Tools
Requires-Python: >=3.11
Requires-Dist: bashlex!=0.13
Requires-Dist: bracex
Requires-Dist: build>=1.0.0
Requires-Dist: certifi
Requires-Dist: dependency-groups>=1.2
Requires-Dist: filelock
Requires-Dist: humanize
Requires-Dist: packaging>=20.9
Requires-Dist: patchelf; (sys_platform == 'linux' or sys_platform == 'darwin') and (platform_machine == 'x86_64' or platform_machine == 'arm64' or platform_machine == 'aarch64')
Requires-Dist: platformdirs
Requires-Dist: pyelftools>=0.29
Requires-Dist: wheel>=0.33.6
Provides-Extra: uv
Requires-Dist: uv; extra == 'uv'
